iSORTlib/SOGlocate.py
iSORTlib/SpaRNA.py
iSORTlib/__init__.py
iSORTlib/iSORT.py
iSORTlib/network.py
iSORTlib/preprocess.py
isortpy-1.0.5.dist-info/LICENSE
isortpy-1.0.5.dist-info/METADATA
isortpy-1.0.5.dist-info/WHEEL
isortpy-1.0.5.dist-info/top_level.txt
isortpy-1.0.5.dist-info/RECORD
